kajiki/__init__.py
kajiki/__main__.py
kajiki/doctype.py
kajiki/html_utils.py
kajiki/i18n.py
kajiki/ir.py
kajiki/lnotab.py
kajiki/loader.py
kajiki/markup_template.py
kajiki/template.py
kajiki/text.py
kajiki/util.py
kajiki/xml_template.py
kajiki/integration/__init__.py
kajiki/integration/pyramid.py
kajiki-1.0.2.dist-info/METADATA
kajiki-1.0.2.dist-info/WHEEL
kajiki-1.0.2.dist-info/entry_points.txt
kajiki-1.0.2.dist-info/licenses/LICENSE.rst
kajiki-1.0.2.dist-info/RECORD
