Metadata-Version: 2.4
Name: kajiki
Version: 1.0.2
Summary: Fast XML-based template engine with Genshi syntax and Jinja blocks
Project-URL: Homepage, https://github.com/jackrosenthal/kajiki
Author-email: Rick Copeland <rick446@usa.net>, Nando Florestan <nandoflorestan@gmail.com>, Alessandro Molina <alessandro@molina.fyi>, Jack Rosenthal <jack@rosenth.al>
Maintainer-email: Jack Rosenthal <jack@rosenth.al>
License-Expression: MIT
License-File: LICENSE.rst
Keywords: chameleon,engine,genshi,html,jinja,jinja2,mako,template,templating,xhtml,xml
Classifier: Development Status :: 5 - Production/Stable
Classifier: Environment :: Web Environment
Classifier: Intended Audience :: Developers
Classifier: License :: OSI Approved :: MIT License
Classifier: Operating System :: OS Independent
Classifier: Programming Language :: Python
Classifier: Programming Language :: Python :: 3
Classifier: Programming Language :: Python :: 3.8
Classifier: Programming Language :: Python :: 3.9
Classifier: Programming Language :: Python :: 3.10
Classifier: Programming Language :: Python :: 3.11
Classifier: Programming Language :: Python :: 3.12
Classifier: Programming Language :: Python :: 3.13
Classifier: Programming Language :: Python :: Implementation :: CPython
Classifier: Programming Language :: Python :: Implementation :: PyPy
Classifier: Topic :: Internet :: WWW/HTTP :: Dynamic Content
Classifier: Topic :: Software Development :: Libraries :: Python Modules
Classifier: Topic :: Text Processing :: Markup :: HTML
Classifier: Topic :: Text Processing :: Markup :: XML
Requires-Python: >=3.8
Requires-Dist: importlib-resources; python_version < '3.9'
Requires-Dist: linetable
